nofex/__init__.py
nofex/nofex.py
nofex_hack-0.0.1.dist-info/LICENSE
nofex_hack-0.0.1.dist-info/METADATA
nofex_hack-0.0.1.dist-info/WHEEL
nofex_hack-0.0.1.dist-info/top_level.txt
nofex_hack-0.0.1.dist-info/RECORD
