Metadata-Version: 2.1
Name: nofex-hack
Version: 0.0.1
Summary: This is a Python library for hacking and security.
Author: kasra kiani
Author-email: kasrakini011@gmail.com
Classifier: Programming Language :: Python :: 3
Classifier: License :: OSI Approved :: MIT License
Classifier: Operating System :: OS Independent
License-File: LICENSE
